halloumi_cross_account_parameter_store/__init__.py
halloumi_cross_account_parameter_store/py.typed
halloumi_cross_account_parameter_store/_jsii/__init__.py
halloumi_cross_account_parameter_store/_jsii/halloumi-cross-account-parameter-store@1.0.1.jsii.tgz
halloumi_cross_account_parameter_store-1.0.1.dist-info/LICENSE
halloumi_cross_account_parameter_store-1.0.1.dist-info/METADATA
halloumi_cross_account_parameter_store-1.0.1.dist-info/WHEEL
halloumi_cross_account_parameter_store-1.0.1.dist-info/top_level.txt
halloumi_cross_account_parameter_store-1.0.1.dist-info/RECORD
