Metadata-Version: 2.1
Name: halloumi-cross-account-parameter-store
Version: 1.0.1
Summary: A custom CDK construct to manage a parameter across an AWS account. This construct creates a Lambda-backed custom resource using AWS CloudFormation that handles assuming a role on the target AWS account and puts, updates or deletes a parameter on that account. Role and parameter related variables are passed to the construct and are used by the function to perform these operations.
Home-page: https://github.com/sentialabs/halloumi-cross-account-parameter-store.git
Author: Sentia MPC<support.mpc@sentia.com>
License: Apache-2.0
Project-URL: Source, https://github.com/sentialabs/halloumi-cross-account-parameter-store.git
Classifier: Intended Audience :: Developers
Classifier: Operating System :: OS Independent
Classifier: Programming Language :: JavaScript
Classifier: Programming Language :: Python :: 3 :: Only
Classifier: Programming Language :: Python :: 3.7
Classifier: Programming Language :: Python :: 3.8
Classifier: Programming Language :: Python :: 3.9
Classifier: Programming Language :: Python :: 3.10
Classifier: Typing :: Typed
Classifier: Development Status :: 5 - Production/Stable
Classifier: License :: OSI Approved
Requires-Python: ~=3.7
License-File: LICENSE
Requires-Dist: aws-cdk-lib (<3.0.0,>=2.37.1)
Requires-Dist: constructs (<11.0.0,>=10.0.5)
Requires-Dist: jsii (<2.0.0,>=1.65.0)
Requires-Dist: publication (>=0.0.3)
Requires-Dist: typeguard (~=2.13.3)
